monsterclient/__init__.py
monsterclient/api.py
monsterclient/monster.py
monsterclient-1.2.1.dist-info/METADATA
monsterclient-1.2.1.dist-info/WHEEL
monsterclient-1.2.1.dist-info/entry_points.txt
monsterclient-1.2.1.dist-info/top_level.txt
monsterclient-1.2.1.dist-info/RECORD
