Metadata-Version: 2.1
Name: monsterclient
Version: 1.2.1
Summary: client for monster
Author-email: Morteza <mortezash404@gmail.com>, Mahrad <mahrad.hanaforoosh@gmail.com>
Classifier: Programming Language :: Python :: 3
Classifier: Programming Language :: Python :: 3.8
Classifier: License :: OSI Approved :: MIT License
Classifier: Operating System :: OS Independent
Requires-Python: >=3.8
Requires-Dist: beautifulsoup4 ==4.12.3
Requires-Dist: bs4 ==0.0.2
Requires-Dist: certifi ==2024.2.2
Requires-Dist: charset-normalizer ==3.3.2
Requires-Dist: click ==8.1.7
Requires-Dist: idna ==3.6
Requires-Dist: Pygments ==2.17.2
Requires-Dist: requests ==2.31.0
Requires-Dist: soupsieve ==2.5
Requires-Dist: urllib3 ==2.2.1
